Workbook
Name Aporte: Invest!$C$11
Name Patrimonio: Invest!$C$14
Name quant_anos: Invest!$C$12
Name Rendimento_carteira: Invest!$G$13
Name Salário: Invest!$G$12
Name Taxa_mensal: Invest!$C$13

Sheet Invest
B2: Horizonte Invest
B10: Planilha de investimento | F10: Configurações
B11: Quanto investir por mês? | C11: 500
B12: Por quantos anos? | C12: 5 | F12: Salário | G12: 5000
B13: Taxa de rendimento real? | C13: 0.01079 | F13: Rendimento da carteira | G13: 0.00901
B14: Patrimônio acumulado? | C14: =FV(Taxa_mensal,quant_anos*12,Aporte*-1) -> 41888.457 | F14: Sugestão de investimento (30%) | G14: =G12*30% -> 1500
B15: Dividendos mensais? | C15: =C14*$G$13 -> 377.415
B18: Cenários | D18: Dividendos
A19: 2 | B19: Quanto em 2 anos? | C19: =FV($C$13,$A19*12,$C$11*-1) -> 13613.814 | D19: =C19*Rendimento_carteira -> 122.66046
A20: 2 | B20: Quanto em 5 anos? | C20: =FV($C$13,$A20*12,$C$11*-1) -> 13613.814 | D20: =C20*Rendimento_carteira -> 122.66046
A21: 2 | B21: Quanto em 10 anos? | C21: =FV($C$13,$A21*12,$C$11*-1) -> 13613.814 | D21: =C21*Rendimento_carteira -> 122.66046
A22: 2 | B22: Quanto em 20 anos? | C22: =FV($C$13,$A22*12,$C$11*-1) -> 13613.814 | D22: =C22*Rendimento_carteira -> 122.66046
A23: 2 | B23: Quanto em 30 anos? | C23: =FV($C$13,$A23*12,$C$11*-1) -> 13613.814 | D23: =C23*Rendimento_carteira -> 122.66046
B26: PERFIL | C26: Moderado
B27: Valor a ser investido por mês | C27: =Aporte -> 500
B29: Tipo de FII | C29: Percentual sugerido | D29: Valores
B30: Papel | C30: =VLOOKUP($C$26&"-"&B30,Base!$A$4:$D$22,3,FALSE) -> 0.32 | D30: =C30*$C$27 -> 160
B31: Tijolo | C31: =VLOOKUP($C$26&"-"&B31,Base!$A$4:$D$22,3,FALSE) -> 0.35 | D31: =C31*$C$27 -> 175
B32: Híbridos | C32: =VLOOKUP($C$26&"-"&B32,Base!$A$4:$D$22,3,FALSE) -> 0.08 | D32: =C32*$C$27 -> 40
B33: FOFs | C33: =VLOOKUP($C$26&"-"&B33,Base!$A$4:$D$22,3,FALSE) -> 0.05 | D33: =C33*$C$27 -> 25
B34: Desenvolvimento | C34: =VLOOKUP($C$26&"-"&B34,Base!$A$4:$D$22,3,FALSE) -> 0.1 | D34: =C34*$C$27 -> 50
B35: Hotelarias | C35: =VLOOKUP($C$26&"-"&B35,Base!$A$4:$D$22,3,FALSE) -> 0.1 | D35: =C35*$C$27 -> 50
D36: =SUM(D30:D35) -> 500

Sheet Base
A4: CHAVE | B4: TIPO DE FII | C4: PERCENTUAL | D4: PERFIL
A5: =D5&"-"&B5 -> Conservador-Papel | B5: Papel | C5: 0.3 | D5: Conservador | H5: Moderado-Tijolo | I5: =VLOOKUP(H5,$A$4:$D$22,3,FALSE) -> 0.35
A6: =D6&"-"&B6 -> Conservador-Tijolo | B6: Tijolo | C6: 0.5 | D6: Conservador
A7: =D7&"-"&B7 -> Conservador-Híbridos | B7: Híbridos | C7: 0.1 | D7: Conservador
A8: =D8&"-"&B8 -> Conservador-FOFs | B8: FOFs | C8: 0.1 | D8: Conservador
A9: =D9&"-"&B9 -> Conservador-Desenvolvimento | B9: Desenvolvimento | C9: 0 | D9: Conservador
A10: =D10&"-"&B10 -> Conservador-Hotelarias | B10: Hotelarias | C10: 0 | D10: Conservador
A11: =D11&"-"&B11 -> Moderado-Papel | B11: Papel | C11: 0.32 | D11: Moderado
A12: =D12&"-"&B12 -> Moderado-Tijolo | B12: Tijolo | C12: 0.35 | D12: Moderado
A13: =D13&"-"&B13 -> Moderado-Híbridos | B13: Híbridos | C13: 0.08 | D13: Moderado
A14: =D14&"-"&B14 -> Moderado-FOFs | B14: FOFs | C14: 0.05 | D14: Moderado
A15: =D15&"-"&B15 -> Moderado-Desenvolvimento | B15: Desenvolvimento | C15: 0.1 | D15: Moderado
A16: =D16&"-"&B16 -> Moderado-Hotelarias | B16: Hotelarias | C16: 0.1 | D16: Moderado
A17: =D17&"-"&B17 -> Agressivo-Papel | B17: Papel | C17: 0.5 | D17: Agressivo
... A22: =D22&"-"&B22 -> Agressivo-Hotelarias | B22: Hotelarias | C22: 0.1 | D22: Agressivo
